ryutils/__init__.py
ryutils/csv_logger.py
ryutils/dict_util.py
ryutils/fmt_util.py
ryutils/json_cache.py
ryutils/log.py
ryutils/mitmproxy_capture.py
ryutils/modern_ssh_tunnel.py
ryutils/path_util.py
ryutils/py.typed
ryutils/requests_helper.py
ryutils/short_url.py
ryutils/system_stats.py
ryutils/text_chunk_reader.py
ryutils/verbose.py
ryutils/worker.py
ryutils/alerts/__init__.py
ryutils/alerts/alert_types.py
ryutils/alerts/alerter.py
ryutils/alerts/discord.py
ryutils/alerts/factory.py
ryutils/alerts/mock.py
ryutils/alerts/slack.py
ryutils/firebase/__init__.py
ryutils/firebase/db_modifier.py
ryutils/firebase/firebase_manager.py
ryutils/firebase/storage.py
ryutils/firebase/collections/__init__.py
ryutils/firebase/collections/base.py
ryutils/sms/__init__.py
ryutils/sms/pytextbelt.py
ryutils-9.0.13.dist-info/licenses/LICENSE
ryutils-9.0.13.dist-info/METADATA
ryutils-9.0.13.dist-info/WHEEL
ryutils-9.0.13.dist-info/top_level.txt
ryutils-9.0.13.dist-info/RECORD
