Metadata-Version: 2.4
Name: ryutils
Version: 9.0.13
Summary: A collection of utilities for Python
Author: Ross Yeager
Author-email: ryeager12@email.com
Classifier: Development Status :: 5 - Production/Stable
Classifier: Intended Audience :: Developers
Classifier: License :: OSI Approved :: MIT License
Classifier: Programming Language :: Python :: 3
Classifier: Programming Language :: Python :: 3.12
License-File: LICENSE
Requires-Dist: deepdiff
Requires-Dist: discord_webhook
Requires-Dist: firebase_admin
Requires-Dist: memory_profiler
Requires-Dist: paramiko
Requires-Dist: psutil
Requires-Dist: pyshorteners
Requires-Dist: pytz
Requires-Dist: slack_sdk
Requires-Dist: types-protobuf
Requires-Dist: types-psutil
Requires-Dist: types-pytz
Dynamic: author
Dynamic: author-email
Dynamic: classifier
Dynamic: description
Dynamic: description-content-type
Dynamic: license-file
Dynamic: requires-dist
Dynamic: summary
